aluno_exatas/__init__.py
aluno_exatas/calc_num/__init__.py
aluno_exatas/calc_num/funcoes_principais.py
aluno_exatas/circuitos_eletricos/__init__.py
aluno_exatas/circuitos_eletricos/componentes_simetricas.py
aluno_exatas/circuitos_eletricos/fasores.py
aluno_exatas/fis_exp/__init__.py
aluno_exatas/fis_exp/classe_mmq.py
aluno_exatas/fis_exp/classe_principal.py
aluno_exatas-0.8.5.dist-info/METADATA
aluno_exatas-0.8.5.dist-info/RECORD
aluno_exatas-0.8.5.dist-info/WHEEL
aluno_exatas-0.8.5.dist-info/top_level.txt
