Metadata-Version: 2.1
Name: aluno-exatas
Version: 0.8.5
Summary: Um pacote para auxiliar alunos de exatas.
Home-page: https://github.com/ericonr/aluno_exatas
Author: EricoNR
Author-email: e170610@g.unicamp.br
License: MIT License
Platform: UNKNOWN
Requires-Dist: numpy
Requires-Dist: sympy
